<?xml version="1.0" ?>
<!--
The contents of this file are subject to the Common Public Attribution
License Version 1.0 (the "License"); you may not use this file except in
compliance with the License. You may obtain a copy of the License at
http://ultimate-empire-at-war.com/cpal. The License is based on the Mozilla
Public License Version 1.1 but Sections 14 and 15 have been added to cover
use of software over a computer network and provide for limited attribution
for the Original Developer. In addition, Exhibit A has been modified to be
consistent with Exhibit B.
    
Software distributed under the License is distributed on an "AS IS" basis,
WITHOUT WARRANTY OF ANY KIND, either express or implied. See the License for
the specific language governing rights and limitations under the License.
    
The Original Code is Ultimate Empire at War.
    
The Original Developer is the Initial Developer. The Initial Developer of the
Original Code is the Ultimate Empire at War team. All portions of the code
written by the Ultimate Empire at War team are Copyright (c) 2012.
All Rights Reserved.
-->
<Story>
	<Event Name="Rebel_Smuggler_00">
		<Event_Type>STORY_ELAPSED</Event_Type>
		<Event_Param1>0</Event_Param1>
		<Story_Dialog>Dialog_E_Intervention_Rebel_Smuggler</Story_Dialog>
		<Story_Chapter>0</Story_Chapter>
		<Story_Dialog_Popup>False</Story_Dialog_Popup>	
		<Story_Tag>Rebel_Smuggler_Tag_00</Story_Tag>
	</Event>
	
	<Event Name="Rebel_Smuggler_01">
		<Event_Type>STORY_DESTROY</Event_Type>
		<Event_Param1>MILLENNIUM_FALCON</Event_Param1>
		<Reward_Type>PLANET_FACTION</Reward_Type>
		<Reward_Param2>Empire</Reward_Param2>
		<Prereq>Rebel_Smuggler_00</Prereq>
		<Story_Dialog>Dialog_E_Intervention_Rebel_Smuggler</Story_Dialog>
		<Story_Chapter>1</Story_Chapter>
		<Story_Dialog_Popup>False</Story_Dialog_Popup>	
	</Event>
		
	<Event Name="Rebel_Smuggler_02">
		<Event_Type>STORY_TRIGGER</Event_Type>
		<Reward_Param>TRIGGER_AI</Reward_Param>
		<Reward_Param1>REBEL_SMUGGLER_NOTIFICATION_00</Reward_Param1>
		<Reward_Param2>Empire</Reward_Param2>
		<Prereq>Rebel_Smuggler_01</Prereq>
	</Event>
	
	<Event Name="Rebel_Smuggler_03">
		<Event_Type>STORY_TRIGGER</Event_Type>
		<Reward_Type>STORY_GOAL_COMPLETED</Reward_Type>
		<Reward_Param1>Rebel_Smuggler_Tag_00</Reward_Param1>
		<Prereq>Rebel_Smuggler_02</Prereq>
	</Event>
	
</Story>
