<?xml version="1.0" ?>
<!--
The contents of this file are subject to the Common Public Attribution
License Version 1.0 (the "License"); you may not use this file except in
compliance with the License. You may obtain a copy of the License at
http://ultimate-empire-at-war.com/cpal. The License is based on the Mozilla
Public License Version 1.1 but Sections 14 and 15 have been added to cover
use of software over a computer network and provide for limited attribution
for the Original Developer. In addition, Exhibit A has been modified to be
consistent with Exhibit B.
    
Software distributed under the License is distributed on an "AS IS" basis,
WITHOUT WARRANTY OF ANY KIND, either express or implied. See the License for
the specific language governing rights and limitations under the License.
    
The Original Code is Ultimate Empire at War.
    
The Original Developer is the Initial Developer. The Initial Developer of the
Original Code is the Ultimate Empire at War team. All portions of the code
written by the Ultimate Empire at War team are Copyright (c) 2012.
All Rights Reserved.
-->
<Story>

   <!-- Wait for two seconds before setting up all the objectives -->
   <Event Name="Sandbox_Set_Sandbox_Objectives">
      <Event_Type>STORY_ELAPSED</Event_Type>
      <Event_Param1>2</Event_Param1>
      <Reward_Type>SET_SANDBOX_OBJECTIVES</Reward_Type>
   </Event>

   <!-- Win the battle objective -->
   <!-- Add objective -->
   <Event Name="Sandbox_Objective_1">
      <Event_Type>STORY_TRIGGER</Event_Type>
      <Reward_Type>ADD_OBJECTIVE</Reward_Type>
      <Reward_Param1></Reward_Param1>
      <Prereq>Sandbox_Set_Sandbox_Objectives</Prereq>
   </Event>

         <!-- Objective complete -->
         <Event Name="Sandbox_Objective_1_Complete">
            <Event_Type>STORY_VICTORY</Event_Type>
            <Event_Param1></Event_Param1>
            <Reward_Type>OBJECTIVE_COMPLETE</Reward_Type>
            <Reward_Param1></Reward_Param1>
            <Prereq>Sandbox_Objective_1</Prereq>
         </Event>


   <!-- Capture the building objective -->
   <!-- Add objective -->
   <Event Name="Sandbox_Objective_2">
      <Event_Type>STORY_TRIGGER</Event_Type>
      <Reward_Type>ADD_OBJECTIVE</Reward_Type>
      <Reward_Param1></Reward_Param1>
      <Prereq>Sandbox_Objective_1</Prereq>
   </Event>

         <!-- Objective complete -->
         <Event Name="Sandbox_Objective_2_Complete">
            <Event_Type>STORY_CAPTURE_STRUCTURE</Event_Type>
            <Event_Param1></Event_Param1>
            <Event_Param2></Event_Param2>
            <Reward_Type>OBJECTIVE_COMPLETE</Reward_Type>
            <Reward_Param1></Reward_Param1>
            <Prereq>Sandbox_Objective_2</Prereq>
         </Event>



   <!-- Turn on objective display -->
   <Event Name="Sandbox_Objective_Display">
      <Event_Type>STORY_TRIGGER</Event_Type>
      <Reward_Type>ENABLE_OBJECTIVE_DISPLAY</Reward_Type>
      <Prereq>Sandbox_Objective_1</Prereq>
   </Event>



   <!-- Protect leader -->
   <!-- This first event is triggered through code -->
   <Event Name="Sandbox_Objective_3_Enable">
      <Event_Type>STORY_TRIGGER</Event_Type>
   </Event>

   <!-- Only trigger this if the first objective has been added and we've enabled it through code -->
   <Event Name="Sandbox_Objective_3">
      <Event_Type>STORY_TRIGGER</Event_Type>
      <Reward_Type>ADD_OBJECTIVE</Reward_Type>
      <Reward_Param1></Reward_Param1>
      <Prereq>Sandbox_Objective_1 Sandbox_Objective_3_Enable</Prereq>
   </Event>

         <!-- Objective complete -->
         <Event Name="Sandbox_Objective_3_Complete">
            <Event_Type>STORY_TRIGGER</Event_Type>
            <Event_Param1></Event_Param1>
            <Reward_Type>OBJECTIVE_COMPLETE</Reward_Type>
            <Reward_Param1></Reward_Param1>
            <Prereq>Sandbox_Objective_3 Sandbox_Objective_1_Complete</Prereq>
         </Event>

         <!-- Check for objective failed -->
         <Event Name="Sandbox_Objective_3_Failed">
            <Event_Type>STORY_TACTICAL_DESTROY</Event_Type>
            <Event_Param1></Event_Param1>
            <Event_Param3></Event_Param3>
            <Reward_Type>OBJECTIVE_FAILED</Reward_Type>
            <Reward_Param1></Reward_Param1>
            <Prereq>Sandbox_Objective_3</Prereq>
         </Event>


   <!-- Kill leader -->
   <!-- This first event is triggered through code -->
   <Event Name="Sandbox_Objective_4_Enable">
      <Event_Type>STORY_TRIGGER</Event_Type>
   </Event>

   <!-- Only trigger this if the first objective has been added and we've enabled it through code -->
   <Event Name="Sandbox_Objective_4">
      <Event_Type>STORY_TRIGGER</Event_Type>
      <Reward_Type>ADD_OBJECTIVE</Reward_Type>
      <Reward_Param1></Reward_Param1>
      <Prereq>Sandbox_Objective_2 Sandbox_Objective_4_Enable</Prereq>
   </Event>

         <!-- Objective complete -->
         <Event Name="Sandbox_Objective_4_Complete">
            <Event_Type>STORY_TACTICAL_DESTROY</Event_Type>
            <Event_Param1></Event_Param1>
            <Event_Param3></Event_Param3>
            <Reward_Type>OBJECTIVE_COMPLETE</Reward_Type>
            <Reward_Param1></Reward_Param1>
            <Prereq>Sandbox_Objective_4</Prereq>
         </Event>

</Story>
